asyncio_rpc/__init__.py
asyncio_rpc/client.py
asyncio_rpc/exceptions.py
asyncio_rpc/models.py
asyncio_rpc/pubsub.py
asyncio_rpc/server.py
asyncio_rpc/commlayers/__init__.py
asyncio_rpc/commlayers/base.py
asyncio_rpc/commlayers/redis.py
asyncio_rpc/serialization/__init__.py
asyncio_rpc/serialization/base.py
asyncio_rpc/serialization/msgpack.py
asyncio_rpc/serialization/shapely_models.py
asyncio_rpc-0.3.2.dist-info/licenses/AUTHORS.rst
asyncio_rpc-0.3.2.dist-info/licenses/LICENSE
asyncio_rpc-0.3.2.dist-info/METADATA
asyncio_rpc-0.3.2.dist-info/WHEEL
asyncio_rpc-0.3.2.dist-info/top_level.txt
asyncio_rpc-0.3.2.dist-info/RECORD
