Metadata-Version: 2.4
Name: asyncio_rpc
Version: 0.3.2
Summary: Asyncio RPC client/server with redis/msgpack/dataclasses
Author-email: Jelle Prins <jelle.prins@nelen-schuurmans.nl>
License: BSD license
Project-URL: Homepage, https://github.com/nens/asyncio-rpc
Classifier: Development Status :: 4 - Beta
Classifier: Intended Audience :: Developers
Classifier: License :: OSI Approved :: BSD License
Classifier: Natural Language :: English
Classifier: Programming Language :: Python :: 3
Classifier: Programming Language :: Python :: 3.10
Classifier: Topic :: Scientific/Engineering
Requires-Python: >=3.10
License-File: LICENSE
License-File: AUTHORS.rst
Requires-Dist: msgpack>=1.0.7
Requires-Dist: lz4>=2.1.6
Requires-Dist: redis[hiredis]<5.0
Provides-Extra: test
Requires-Dist: pytest; extra == "test"
Requires-Dist: pytest-asyncio; extra == "test"
Provides-Extra: numpy
Requires-Dist: numpy==1.26.*; extra == "numpy"
Provides-Extra: shapely
Requires-Dist: shapely>=2.0.1; extra == "shapely"
Provides-Extra: dev
Requires-Dist: ipdb; extra == "dev"
Requires-Dist: mypy; extra == "dev"
Requires-Dist: ruff; extra == "dev"
Dynamic: license-file
